setup.py
sPyNNakerExternalDevicesPlugin.egg-info/PKG-INFO
sPyNNakerExternalDevicesPlugin.egg-info/SOURCES.txt
sPyNNakerExternalDevicesPlugin.egg-info/dependency_links.txt
sPyNNakerExternalDevicesPlugin.egg-info/requires.txt
sPyNNakerExternalDevicesPlugin.egg-info/top_level.txt
spynnaker_external_devices_plugin/__init__.py
spynnaker_external_devices_plugin/pyNN/__init__.py
spynnaker_external_devices_plugin/pyNN/spynnaker_external_device_plugin_manager.py
spynnaker_external_devices_plugin/pyNN/connections/__init__.py
spynnaker_external_devices_plugin/pyNN/connections/spynnaker_live_spikes_connection.py
spynnaker_external_devices_plugin/pyNN/external_devices_models/__init__.py
spynnaker_external_devices_plugin/pyNN/external_devices_models/external_cochlea_device.py
spynnaker_external_devices_plugin/pyNN/external_devices_models/external_fpga_retina_device.py
spynnaker_external_devices_plugin/pyNN/external_devices_models/munich_motor_device.py
spynnaker_external_devices_plugin/pyNN/external_devices_models/munich_retina_device.py
spynnaker_external_devices_plugin/pyNN/external_devices_models/pushbot_retina_device.py
spynnaker_external_devices_plugin/pyNN/model_binaries/__init__.py
spynnaker_external_devices_plugin/pyNN/model_binaries/robot_motor_control.aplx
spynnaker_external_devices_plugin/pyNN/utility_models/__init__.py
spynnaker_external_devices_plugin/pyNN/utility_models/spike_injector.py