Metadata-Version: 1.0
Name: sPyNNakerExternalDevicesPlugin
Version: 2016.001
Summary: Spinnaker External Devices Plugin
Home-page: https://github.com/SpiNNakerManchester/SpyNNaker
Author: UNKNOWN
Author-email: UNKNOWN
License: UNKNOWN
Platform: UNKNOWN
